{
    "imports": [
        {
            "form": "us_1040",
            "line": "L11",
            "year": 2024
        }
    ],
    "inputs": [
        0,
        1,
        2,
        3,
        4,
        5,
        6,
        7,
        8,
        9
    ],
    "meta": {
        "form_id": "ky_740",
        "generated_by": "tenforty-dsl",
        "year": 2024
    },
    "nodes": {
        "0": {
            "id": 0,
            "name": "L6_ky_additions",
            "op": {
                "type": "input"
            }
        },
        "1": {
            "id": 1,
            "name": "L8_ky_subtractions",
            "op": {
                "type": "input"
            }
        },
        "10": {
            "id": 10,
            "op": {
                "form": "us_1040",
                "line": "L11",
                "type": "import",
                "year": 2024
            }
        },
        "11": {
            "id": 11,
            "op": {
                "type": "literal",
                "value": 0
            }
        },
        "12": {
            "id": 12,
            "name": "L5_federal_agi",
            "op": {
                "left": 10,
                "right": 11,
                "type": "add"
            }
        },
        "13": {
            "id": 13,
            "name": "L7_total_with_additions",
            "op": {
                "left": 12,
                "right": 0,
                "type": "add"
            }
        },
        "14": {
            "id": 14,
            "op": {
                "type": "literal",
                "value": 0
            }
        },
        "15": {
            "id": 15,
            "op": {
                "left": 13,
                "right": 1,
                "type": "sub"
            }
        },
        "16": {
            "id": 16,
            "name": "L9_ky_agi",
            "op": {
                "left": 14,
                "right": 15,
                "type": "max"
            }
        },
        "17": {
            "id": 17,
            "name": "L10_std",
            "op": {
                "type": "literal",
                "value": 3160
            }
        },
        "18": {
            "id": 18,
            "name": "L10_total",
            "op": {
                "left": 2,
                "right": 17,
                "type": "max"
            }
        },
        "19": {
            "id": 19,
            "op": {
                "type": "literal",
                "value": 0
            }
        },
        "2": {
            "id": 2,
            "name": "L10_ky_itemized_deductions",
            "op": {
                "type": "input"
            }
        },
        "20": {
            "id": 20,
            "op": {
                "left": 16,
                "right": 18,
                "type": "sub"
            }
        },
        "21": {
            "id": 21,
            "name": "L11_ky_taxable_income",
            "op": {
                "left": 19,
                "right": 20,
                "type": "max"
            }
        },
        "22": {
            "id": 22,
            "op": {
                "type": "literal",
                "value": 4.0e-2
            }
        },
        "23": {
            "id": 23,
            "name": "L12_ky_tax",
            "op": {
                "left": 21,
                "right": 22,
                "type": "mul"
            }
        },
        "24": {
            "id": 24,
            "name": "L16_total_nonrefundable_credits",
            "op": {
                "left": 3,
                "right": 4,
                "type": "add"
            }
        },
        "25": {
            "id": 25,
            "op": {
                "type": "literal",
                "value": 0
            }
        },
        "26": {
            "id": 26,
            "op": {
                "left": 23,
                "right": 24,
                "type": "sub"
            }
        },
        "27": {
            "id": 27,
            "name": "L17_balance_of_tax",
            "op": {
                "left": 25,
                "right": 26,
                "type": "max"
            }
        },
        "28": {
            "id": 28,
            "name": "L19_total_tax",
            "op": {
                "left": 27,
                "right": 5,
                "type": "add"
            }
        },
        "29": {
            "id": 29,
            "op": {
                "left": 8,
                "right": 9,
                "type": "add"
            }
        },
        "3": {
            "id": 3,
            "name": "L13_family_size_credit",
            "op": {
                "type": "input"
            }
        },
        "30": {
            "id": 30,
            "op": {
                "left": 7,
                "right": 29,
                "type": "add"
            }
        },
        "31": {
            "id": 31,
            "name": "L24_total_payments",
            "op": {
                "left": 6,
                "right": 30,
                "type": "add"
            }
        },
        "32": {
            "id": 32,
            "op": {
                "left": 31,
                "right": 28,
                "type": "sub"
            }
        },
        "33": {
            "id": 33,
            "op": {
                "left": 31,
                "right": 28,
                "type": "sub"
            }
        },
        "34": {
            "id": 34,
            "op": {
                "type": "literal",
                "value": 0
            }
        },
        "35": {
            "id": 35,
            "name": "L25_refund",
            "op": {
                "cond": 32,
                "otherwise": 34,
                "then": 33,
                "type": "if_positive"
            }
        },
        "36": {
            "id": 36,
            "op": {
                "type": "literal",
                "value": 0
            }
        },
        "37": {
            "id": 37,
            "op": {
                "left": 28,
                "right": 31,
                "type": "sub"
            }
        },
        "38": {
            "id": 38,
            "name": "L26_amount_owed",
            "op": {
                "left": 36,
                "right": 37,
                "type": "max"
            }
        },
        "4": {
            "id": 4,
            "name": "L15_other_nonrefundable_credits",
            "op": {
                "type": "input"
            }
        },
        "5": {
            "id": 5,
            "name": "L18_llet",
            "op": {
                "type": "input"
            }
        },
        "6": {
            "id": 6,
            "name": "L20_ky_tax_withheld",
            "op": {
                "type": "input"
            }
        },
        "7": {
            "id": 7,
            "name": "L21_estimated_payments",
            "op": {
                "type": "input"
            }
        },
        "8": {
            "id": 8,
            "name": "L22_extension_payment",
            "op": {
                "type": "input"
            }
        },
        "9": {
            "id": 9,
            "name": "L23_refundable_credits",
            "op": {
                "type": "input"
            }
        }
    },
    "outputs": [
        21,
        23,
        28,
        31,
        35,
        38,
        12,
        16
    ],
    "tables": {}
}
